cvtools/__init__.py
cvtools/cvtypes.py
cvtools/extras/__init__.py
cvtools/extras/clustering.py
cvtools/extras/imgproc.py
cvtools/extras/iterators.py
cvtools/extras/matlab.py
cvtools/imgio.py
cvtools/py.typed
cvtools/videoio.py
cvtools_alkasm-1.0.2.dist-info/LICENSE
cvtools_alkasm-1.0.2.dist-info/WHEEL
cvtools_alkasm-1.0.2.dist-info/METADATA
cvtools_alkasm-1.0.2.dist-info/RECORD
